Workbook

Sheet Read me
A1: Survey of U.S. Household Technology-Adoption Incentives: Federal and 50 States
A2: Compiled June 2026. Framing: evidence on the generalizability of a forward-looking durable-goods adoption model across incentivized household technologies.
A4: Model-feature coding scheme
A5: Each program is coded on the four structural features of the adoption model. Codes: Y (feature present), Partial (feature present but attenuated), No (feature absent). Codes for NPV and Visibility are assigned by technology; codes for the time path and timing features are assigned from the incentive mechanism and current program status. These are analyst codings to support qualitative pattern-matching, not program attributes claimed by the administrators.
A6: 1. NPV durable good. The incentive targets a durable asset whose adoption rests on the net present value of a future benefit stream weighed against an upfront cost (solar, storage, EVs, heat pumps, weatherization, panels). Weaker (Partial) for appliances, EV chargers, water-efficiency retrofits, and smart thermostats; absent for broadband service subsidies.
A7: 2. Time-varying incentive path. The incentive amount changes over time through a scheduled step-down (block-declining tariffs, ITC schedules), a statutory sunset, or budget-driven exhaustion and reservation. Net-metering and net-billing rates are coded Partial because they are revised through periodic regulatory dockets. Stable sales- and property-tax exemptions are coded No.
A8: 3. Visibility / peer effects. The adopted technology is socially observable to neighbors, generating the visibility channel for peer contagion (rooftop solar, EVs, exterior heat-pump and turf installations). Absent for insulation, panels, water heaters, appliances, and broadband.
A9: 4. Forward-looking timing. The incentive creates an intertemporal incentive to time adoption strategically, through announced deadlines, scheduled declines, or act-before-funds-are-gone budget constraints (waitlists, reservations, first-come funding).
A11: Federal note: The One Big Beautiful Bill Act (PL 119-21, July 4, 2025) terminated the Sec. 25D residential clean-energy credit and the Sec. 25C efficiency credit after 12/31/2025, and the Sec. 30D and 25E vehicle credits after 9/30/2025. The Sec. 30C charger credit sunsets 6/30/2026. These sunsets are themselves a vivid instance of features 2 and 4.
A12: Coverage note: State coverage captures the flagship statewide and major-utility household programs per technology category, drawn from DSIRE and administrator pages. It is representative of each state's regime, not an exhaustive enumeration of every municipal or water-utility line item. Dollar amounts and statuses change with program years; the linked source is authoritative.
A14: Sheets: 'All programs' (full filterable matrix, federal + state) and 'Summary' (counts by technology, mechanism, status, and feature).

Sheet All programs
A1: Jurisdiction | B1: State | C1: Program | D1: Administrator | E1: Technology | F1: Mechanism | G1: Amount / rate | H1: Eligibility | I1: Status (June 2026) | J1: NPV durable good | K1: Time-varying path | L1: Visibility / peer | M1: Forward-looking timing | N1: Source URL
A2: Federal | B2: US | C2: Sec. 25D Residential Clean Energy Credit | D2: IRS / U.S. Treasury | E2: Solar PV; battery storage; geothermal; small wind; fuel cell | F2: Tax credit | G2: 30% of system cost, no cap | H2: Homeowners, all incomes | I2: TERMINATED - no credit for expenditures after 12/31/2025 (PL 119-21) | J2: Y | K2: Y | L2: Y | M2: Y | N2: link
A3: Federal | B3: US | C3: Sec. 25C Energy Efficient Home Improvement Credit | D3: IRS / U.S. Treasury | E3: Heat pumps; HPWH; insulation; windows; doors; panels; audits | F3: Tax credit | G3: 30% of cost; up to $1,200/yr (+$2,000 for heat pumps) | H3: Homeowners | I3: TERMINATED - not allowed for property placed in service after 12/31/2025 (PL 119-21) | J3: Y | K3: Y | L3: Partial | M3: Y | N3: link
A4: Federal | B4: US | C4: Sec. 30D Clean Vehicle Credit | D4: IRS / U.S. Treasury | E4: Electric vehicles (new) | F4: Tax credit | G4: Up to $7,500 | H4: Income and MSRP caps | I4: TERMINATED - vehicles acquired after 9/30/2025 ineligible (PL 119-21) | J4: Y | K4: Y | L4: Y | M4: Y | N4: link
A5: Federal | B5: US | C5: Sec. 25E Previously-Owned Clean Vehicle Credit | D5: IRS / U.S. Treasury | E5: Electric vehicles (used) | F5: Tax credit | G5: Up to $4,000 (30% of price) | H5: Income caps; price <= $25,000 | I5: TERMINATED - vehicles acquired after 9/30/2025 ineligible (PL 119-21) | J5: Y | K5: Y | L5: Y | M5: Y | N5: link
A6: Federal | B6: US | C6: Sec. 30C Alt. Fuel Vehicle Refueling Property Credit | D6: IRS / U.S. Treasury | E6: EV chargers | F6: Tax credit | G6: 30% of hardware+install, up to $1,000 residential | H6: Property in eligible census tracts | I6: ACTIVE but sunsetting - must be placed in service by 6/30/2026 (PL 119-21) | J6: Partial | K6: Y | L6: Partial | M6: Y | N6: link
A7: Federal | B7: US | C7: Home Electrification & Appliance Rebates (HEAR, IRA Sec. 50122) | D7: U.S. DOE via state energy offices | E7: Heat pumps; HPWH; panel; wiring; weatherization; ENERGY STAR appliances | F7: Point-of-sale rebate | G7: Up to $14,000/household (e.g., $8,000 heat pump, $1,750 HPWH, $4,000 panel) | H7: Income-limited (<= 150% AMI) | I7: ACTIVE - state-administered, staggered 2025-2026 rollout | J7: Y | K7: Partial | L7: Partial | M7: Partial | N7: link
A8: Federal | B8: US | C8: Home Efficiency Rebates (HOMES, IRA Sec. 50121) | D8: U.S. DOE via state energy offices | E8: Whole-home efficiency; weatherization | F8: Performance rebate | G8: Up to $8,000 (modeled/measured energy savings) | H8: All incomes; larger awards for low income | I8: ACTIVE - state-administered, staggered 2025-2026 rollout | J8: Y | K8: Y | L8: No | M8: Y | N8: link
A9: Federal | B9: US | C9: Weatherization Assistance Program (WAP) | D9: U.S. DOE / states / community action agencies | E9: Weatherization; insulation; HVAC; heat pumps | F9: Grant (free upgrades) | G9: Avg ~$6,500 per dwelling unit | H9: Income-limited (typically <= 200% FPL) | I9: ACTIVE - FY2026 ~$329M; funding restored post-shutdown | J9: Y | K9: Partial | L9: Partial | M9: Partial | N9: link
A10: Federal | B10: US | C10: Low Income Home Energy Assistance Program (LIHEAP) | D10: U.S. HHS / Administration for Children & Families | E10: Heating/cooling bill assistance; some weatherization | F10: Grant / bill subsidy | G10: Varies by state and need | H10: Income-limited | I10: ACTIVE - ~$4.05B appropriated through FY2026 | J10: Y | K10: Partial | L10: No | M10: Partial | N10: link
A11: Federal | B11: US | C11: Lifeline Program | D11: FCC / Universal Service Fund | E11: Broadband and voice service | F11: Bill subsidy | G11: $9.25/mo ($34.25 on Tribal lands) | H11: Income- or program-eligible (SNAP, Medicaid, SSI, etc.) | I11: ACTIVE | J11: No | K11: Partial | L11: No | M11: Partial | N11: link
A12: Federal | B12: US | C12: Affordable Connectivity Program (ACP) | D12: FCC | E12: Broadband service | F12: Bill subsidy | G12: $30/mo ($75 Tribal) | H12: Income-eligible (<= 200% FPL) | I12: TERMINATED - funds exhausted, program ended mid-2024; not renewed | J12: No | K12: Y | L12: No | M12: Y | N12: link
... A222: State | B222: HI | C222: Green Energy Money Saver (GEMS) | D222: Hawaii Green Infrastructure Authority | E222: Solar; storage; efficiency | F222: Loan (on-bill) | G222: Low-cost on-bill financing | H222: Underserved/renters/low-income | I222: Active | J222: Y | K222: Partial | L222: Partial | M222: Partial | N222: link

Sheet Summary
A1: Summary statistics
A2: Total programs catalogued | B2: 221
A4: Technology category | B4: Count | D4: Mechanism | E4: Count | G4: Status / model feature | H4: Count
A5: Solar PV | B5: =COUNTIF('All programs'!E2:E222,"*Solar PV*") -> 89 | D5: Tax credit | E5: =COUNTIF('All programs'!F2:F222,"*Tax credit*") -> 20 | G5: Terminated/closed programs | H5: =COUNTIF('All programs'!I2:I222,"*TERMINATED*")+COUNTIF('All programs'!I2:I222,"*CLOSED*")+COUNTIF('All programs'!I2:I222,"*Closed*") -> 19
A6: Battery storage | B6: =COUNTIF('All programs'!E2:E222,"*Battery storage*") -> 22 | D6: Tax exemption | E6: =COUNTIF('All programs'!F2:F222,"*Tax exemption*") -> 19 | G6: Pending / launching | H6: =COUNTIF('All programs'!I2:I222,"*ending*")+COUNTIF('All programs'!I2:I222,"*aunching*")+COUNTIF('All programs'!I2:I222,"*olling*") -> 12
A7: Electric vehicles | B7: =COUNTIF('All programs'!E2:E222,"*Electric vehicles*") -> 19 | D7: Rebate | E7: =COUNTIF('All programs'!F2:F222,"*Rebate*") -> 107 | G7: Waitlist / reserved / depleted | H7: =COUNTIF('All programs'!I2:I222,"*aitlist*")+COUNTIF('All programs'!I2:I222,"*eserved*")+COUNTIF('All programs'!I2:I222,"*eplet*") -> 10
A8: EV chargers | B8: =COUNTIF('All programs'!E2:E222,"*EV chargers*") -> 9 | D8: Grant | E8: =COUNTIF('All programs'!F2:F222,"*Grant*") -> 13 | G8: NPV durable good = Y | H8: =COUNTIF('All programs'!J2:J222,"Y") -> 193
A9: Heat pumps | B9: =COUNTIF('All programs'!E2:E222,"*Heat pumps*") -> 56 | D9: Loan | E9: =COUNTIF('All programs'!F2:F222,"*Loan*") -> 8 | G9: Time-varying path = Y | H9: =COUNTIF('All programs'!K2:K222,"Y") -> 52
A10: HPWH | B10: =COUNTIF('All programs'!E2:E222,"*HPWH*") -> 19 | D10: Net metering | E10: =COUNTIF('All programs'!F2:F222,"*Net metering*") -> 30 | G10: Visibility/peer = Y | H10: =COUNTIF('All programs'!L2:L222,"Y") -> 108
A11: Weatherization | B11: =COUNTIF('All programs'!E2:E222,"*Weatherization*") -> 38 | D11: Net billing | E11: =COUNTIF('All programs'!F2:F222,"*Net billing*") -> 9 | G11: Forward-looking timing = Y | H11: =COUNTIF('All programs'!M2:M222,"Y") -> 47
A12: Appliances | B12: =COUNTIF('All programs'!E2:E222,"*Appliances*") -> 31 | D12: Performance | E12: =COUNTIF('All programs'!F2:F222,"*Performance*") -> 21 | G12: All four features present (Y) | H12: =SUMPRODUCT(('All programs'!J2:J222="Y")*('All programs'!K2:K222="Y")*('All programs'!L2:L222="Y")*('All programs'!M2:M222="Y")) -> 21
A13: Panel | B13: =COUNTIF('All programs'!E2:E222,"*Panel*") -> 17 | D13: Subsidy | E13: =COUNTIF('All programs'!F2:F222,"*Subsidy*") -> 4
A14: Water efficiency | B14: =COUNTIF('All programs'!E2:E222,"*Water efficiency*") -> 5 | D14: Deduction | E14: =COUNTIF('All programs'!F2:F222,"*Deduction*") -> 1
A15: Broadband | B15: =COUNTIF('All programs'!E2:E222,"*Broadband*") -> 5
A16: Smart thermostat | B16: =COUNTIF('All programs'!E2:E222,"*Smart thermostat*") -> 10
